Workbook

Sheet Welcome
B2: Jaspen Decision Workbook
B3: One important decision, thought through clearly.
B5: This workbook gives you a calm, structured place to work through a single important decision — from framing the problem to capturing what you finally chose and why. Work top to bottom through the four steps, then share or print the Decision Summary.
B7: How to use it
B8: Step 1 — Frame the decision: what you are deciding, by when, and why it matters.
B9: Step 2 — Compare options: list your choices, weight what matters, and score each one. The workbook does the math.
B10: Step 3 — Evidence & risks: capture what supports and challenges each option, the trade-offs, and how confident you are.
B11: Step 4 — Decide & review: record your final choice, why you made it, and a date to check how it turned out.
B12: Decision Summary: a clean one-page view that fills itself in from your answers — good for sharing or printing.
B14: This workbook vs. Jaspen
B15: This workbook helps you organize your thinking by hand — you bring the structure and do the writing. Jaspen does it with you: it interviews you about the decision, surfaces assumptions and trade-offs you might miss, scores your options deterministically, and preserves the whole reasoning as a Decision Record you can return to.
A17: Prefer to think it through out loud? Jaspen walks you through this same method interactively — it asks the follow-up questions, surfaces the assumptions and trade-offs you might miss, scores your options, and keeps the reasoning so you can revisit it later. Try it free at jaspen.ai

Sheet 1. Frame the Decision
A1: Jaspen Decision Workbook
A2: Step 1 of 4 · Frame the decision
A4: Define the decision | B4: One clear sentence. A real choice, not a vague topic.
A5: Should we hire a full-time operations manager, or keep using a contractor?
A7: Decision deadline | B7: When does this need to be decided by?
A8: 2026-08-15
A10: Why this decision matters | B10: What is really at stake — for you, the team, or the business.
A11: Delivery is slipping and we keep losing evenings to firefighting. The right call frees up leadership time.
A13: What happens if no decision is made | B13: The cost of drift. Naming it makes the deadline real.
A14: We keep paying premium contractor rates and stay stuck reacting instead of planning.
A16: Desired outcome | B16: What a good result looks like a few months from now.
A17: Operations run smoothly without daily leadership involvement, within budget.
A19: Options being considered | B19: List the choices on the table. You will compare them in Step 2.
A20: Option | B20: Short name (used in Step 2) | C20: Description
A21: Option A | B21: Full-time hire | C21: Hire a full-time operations manager.
A22: Option B | B22: Contractor | C22: Keep the current contractor on a monthly retainer.
A23: Option C | B23: Promote internally | C23: Promote and train an existing team member.
A24: Option D
A25: Option E
A27: Tip: two or three real options is plenty. Too many and nothing gets compared properly.

Sheet 2. Compare Options
A1: Jaspen Decision Workbook
A2: Step 2 of 4 · Compare your options
A4: Weight what matters, score each option 0–100, and the workbook ranks them for you. Weights should add up to 100%.
A6: Criterion | B6: Weight % | C6: =IF('1. Frame the Decision'!B21="","",'1. Frame the Decision'!B21) | D6: =IF('1. Frame the Decision'!B22="","",'1. Frame the Decision'!B22) | E6: =IF('1. Frame the Decision'!B23="","",'1. Frame the Decision'!B23) | F6: =IF('1. Frame the Decision'!B24="","",'1. Frame the Decision'!B24) | G6: =IF('1. Frame the Decision'!B25="","",'1. Frame the Decision'!B25)
A7: Cost / budget fit | B7: 25 | C7: 70 | D7: 85 | E7: 75
A8: Speed to results | B8: 20 | C8: 80 | D8: 60 | E8: 55
A9: Quality & reliability | B9: 20 | C9: 85 | D9: 65 | E9: 70
A10: Team capacity freed | B10: 20 | C10: 90 | D10: 50 | E10: 60
A11: Risk & reversibility | B11: 15 | C11: 65 | D11: 80 | E11: 70
A13: Total weight | B13: =SUM(B7:B12) | C13: =IF(B13=100,"Balanced — weights add up to 100%","Adjust weights to total 100%")
A15: Weighted score | C15: =IF(COUNT(C7:C12)=0,"",ROUND(SUMPRODUCT($B7:$B12,C7:C12)/IF(SUM($B7:$B12)=0,1,SUM($B7:$B12)),0)) | D15: =IF(COUNT(D7:D12)=0,"",ROUND(SUMPRODUCT($B7:$B12,D7:D12)/IF(SUM($B7:$B12)=0,1,SUM($B7:$B12)),0)) | E15: =IF(COUNT(E7:E12)=0,"",ROUND(SUMPRODUCT($B7:$B12,E7:E12)/IF(SUM($B7:$B12)=0,1,SUM($B7:$B12)),0)) | F15: =IF(COUNT(F7:F12)=0,"",ROUND(SUMPRODUCT($B7:$B12,F7:F12)/IF(SUM($B7:$B12)=0,1,SUM($B7:$B12)),0)) | G15: =IF(COUNT(G7:G12)=0,"",ROUND(SUMPRODUCT($B7:$B12,G7:G12)/IF(SUM($B7:$B12)=0,1,SUM($B7:$B12)),0))
A17: Leading option | B17: =IF(COUNT(C15:G15)=0,"Score your options above",INDEX(C6:G6,MATCH(MAX(C15:G15),C15:G15,0))) | E17: highest score: | F17: =IF(COUNT(C15:G15)=0,"",MAX(C15:G15))
A19: The leading option is just the math on your inputs — it is a prompt for judgment, not the final word. Sanity-check it in Step 3 before you commit.

Sheet 3. Evidence & Risks
A1: Jaspen Decision Workbook
A2: Step 3 of 4 · Pressure-test your thinking
A4: Assumptions | B4: What are you taking as true that you have not actually confirmed?
A5: We assume a full-time hire can be productive within a month, and that budget holds through Q4.
A7: Evidence that supports your leading option | B7: Facts, data, or experience that back it up.
A8: Two peers who made a full-time hire cut their firefighting time noticeably within a quarter.
A10: Evidence that challenges it | B10: What argues against it? Be honest here — this is where good decisions are made.
A11: Our volume may not justify a full-time salary yet; a contractor stays flexible if things change.
A13: Trade-offs | B13: What you give up with the leading option.
A14: More fixed cost and commitment in exchange for continuity and freed-up leadership time.
A16: Risks | B16: What could go wrong, and how bad would it be?
A17: A wrong hire is slow and costly to unwind. Mitigate with a clear 90-day plan and check-ins.
A19: Confidence level | B19: How sure are you, given the evidence above? High / Medium / Low.
A20: Medium
A22: What information would change your decision? | B22: Name it now. If you can get it before the deadline, do.
A23: A clear 3-month forecast of workload — if volume is trending down, the contractor wins.

Sheet 4. Decide & Review
A1: Jaspen Decision Workbook
A2: Step 4 of 4 · Make the call
A4: Final choice | B4: The option you are committing to. It is okay to differ from the leading score — say why below.
A5: Full-time hire
A7: Why this choice was made | B7: The reasoning you would want to reread in six months.
A8: It frees the most leadership time and scored highest, and the 90-day plan limits the downside.
A10: Review date | B10: When will you check how this turned out?
A11: 2026-11-15
A13: Outcome and lessons learned | B13: Fill this in on your review date. This is how the next decision gets better.
A14: (Come back on your review date and record what actually happened and what you would do differently.)

Sheet Decision Summary
A1: Decision Summary
A2: A one-page view of your decision. It fills itself in from the other sheets — good for sharing or printing.
A4: The decision | B4: ='1. Frame the Decision'!A5
A5: Why it matters | B5: ='1. Frame the Decision'!A11
A6: Desired outcome | B6: ='1. Frame the Decision'!A17
A7: Deadline | B7: ='1. Frame the Decision'!A8
A8: Leading option (by score) | B8: =IF('2. Compare Options'!B17="","Complete Step 2",'2. Compare Options'!B17&" ("&TEXT('2. Compare Options'!F17,"0")&"/100)")
A9: Final choice | B9: =IF('4. Decide & Review'!A5="","Complete Step 4",'4. Decide & Review'!A5)
A10: Why this choice | B10: ='4. Decide & Review'!A8
A11: Confidence | B11: =IF('3. Evidence & Risks'!A20="","—",'3. Evidence & Risks'!A20)
A12: Review date | B12: ='4. Decide & Review'!A11
A13: Outcome & lessons | B13: =IF('4. Decide & Review'!A15="","To be completed on your review date",'4. Decide & Review'!A15)
A15: Prefer to think it through out loud? Jaspen walks you through this same method interactively — it asks the follow-up questions, surfaces the assumptions and trade-offs you might miss, scores your options, and keeps the reasoning so you can revisit it later. Try it free at jaspen.ai
