Workbook

Sheet Welcome
B2: Jaspen Decision Planning Toolkit
B3: Think through one important decision — clearly, and together.
B5: Big decisions usually live in scattered places — a few notes here, a hallway conversation there, a trade-off someone mentioned once. This toolkit gives you one calm place to lay it all out: what you're deciding, what matters, the options on the table, the assumptions underneath them, and the reasoning behind your final call.
B6: Use it on your own to get your head straight, or pass it around so your whole team's thinking is in one place before you decide.
B8: How to use it
B9: Step 1 — Frame the decision: what you're deciding, by when, and why it matters.
B10: Step 2 — Your rubric: name what matters, weight it, and score each option. The toolkit does the math.
B11: Step 3 — Assumptions & evidence: surface what you're assuming, then weigh what the evidence actually says.
B12: Step 4 — Decide & review: record your call, why you made it, and a date to see how it turned out.
B13: Decision Summary: a clean one-page view that fills itself in — ready to share or print.
B15: Organize your thinking here. Pressure-test it in Jaspen.
B16: A workbook is great at holding your thinking. What it can't do is question it. Once you've laid things out here, Jaspen takes it further — it asks the follow-up questions a spreadsheet can't, surfaces the assumptions and blind spots that are easy to miss, and keeps your reasoning as a Decision Record you can return to. Think of this toolkit as step one, and a Jaspen session as the conversation that pressure-tests it.
B17: Working across a team? Have Operations, Finance, and Legal each add their piece here, then bring the whole picture together in one place.
A19: When you're ready to pressure-test your thinking, continue at jaspen.ai

Sheet 1. Frame the Decision
A1: Jaspen Decision Planning Toolkit
A2: Step 1 of 4 · Frame the decision
A4: What are you deciding? | B4: One plain sentence. A real choice you're facing — not a broad topic.
A5: Should we hire a full-time operations manager, or keep using our contractor?
A7: When do you need to decide? | B7: A real date keeps the decision from drifting.
A8: 2026-08-15
A10: Why does this matter? | B10: What's really at stake — for you, your team, or the business — if you get it right or wrong?
A11: Delivery keeps slipping and we're losing evenings to firefighting. The right call frees up real leadership time.
A13: What happens if you don't decide? | B13: The cost of letting it drift. Naming it makes the deadline feel real.
A14: We keep paying premium contractor rates and stay stuck reacting instead of planning ahead.
A16: What would a good outcome look like? | B16: Picture a few months out. What does 'this went well' actually look like?
A17: Operations run smoothly without daily leadership involvement, and we're still within budget.
A19: What options are you weighing? | B19: The choices on the table. You'll score them against your rubric in Step 2.
A20: Option | B20: Short name (used in Step 2) | C20: What it is
A21: Option A | B21: Full-time hire | C21: Hire a full-time operations manager.
A22: Option B | B22: Contractor | C22: Keep our current contractor on a monthly retainer.
A23: Option C | B23: Promote from within | C23: Promote and train someone already on the team.
A24: Option D
A25: Option E
A27: Two or three real options is usually plenty. Too many and nothing gets a fair look.

Sheet 2. Your Rubric
A1: Jaspen Decision Planning Toolkit
A2: Step 2 of 4 · Your decision rubric
A4: A rubric is simply what matters to you, and how much. Edit the criteria, set the weights, and score each option from 0–100 — it's yours to change. The toolkit adds it up.
A5: This is a starting example — replace it with your own. Only the shaded cells calculate for you.
A7: What matters (your criteria) | B7: Weight % | C7: =IF('1. Frame the Decision'!B21="","",'1. Frame the Decision'!B21) | D7: =IF('1. Frame the Decision'!B22="","",'1. Frame the Decision'!B22) | E7: =IF('1. Frame the Decision'!B23="","",'1. Frame the Decision'!B23) | F7: =IF('1. Frame the Decision'!B24="","",'1. Frame the Decision'!B24) | G7: =IF('1. Frame the Decision'!B25="","",'1. Frame the Decision'!B25)
A8: Frees up leadership time | B8: 25 | C8: 90 | D8: 50 | E8: 60
A9: Fits the budget | B9: 25 | C9: 70 | D9: 85 | E9: 75
A10: Speed to results | B10: 20 | C10: 80 | D10: 60 | E10: 55
A11: Quality & reliability | B11: 15 | C11: 85 | D11: 65 | E11: 70
A12: Easy to change course later | B12: 15 | C12: 65 | D12: 80 | E12: 70
A16: Total weight | B16: =SUM(B8:B15) | C16: =IF(B16=100,"Nice — your weights add up to 100%","Aim for 100% total (currently off)")
A18: Weighted score | C18: =IF(COUNT(C8:C15)=0,"",ROUND(SUMPRODUCT($B8:$B15,C8:C15)/IF(SUM($B8:$B15)=0,1,SUM($B8:$B15)),0)) | D18: =IF(COUNT(D8:D15)=0,"",ROUND(SUMPRODUCT($B8:$B15,D8:D15)/IF(SUM($B8:$B15)=0,1,SUM($B8:$B15)),0)) | E18: =IF(COUNT(E8:E15)=0,"",ROUND(SUMPRODUCT($B8:$B15,E8:E15)/IF(SUM($B8:$B15)=0,1,SUM($B8:$B15)),0)) | F18: =IF(COUNT(F8:F15)=0,"",ROUND(SUMPRODUCT($B8:$B15,F8:F15)/IF(SUM($B8:$B15)=0,1,SUM($B8:$B15)),0)) | G18: =IF(COUNT(G8:G15)=0,"",ROUND(SUMPRODUCT($B8:$B15,G8:G15)/IF(SUM($B8:$B15)=0,1,SUM($B8:$B15)),0))
A20: Leading option | B20: =IF(COUNT(C18:G18)=0,"Score your options above",INDEX(C7:G7,MATCH(MAX(C18:G18),C18:G18,0))) | E20: highest score: | F20: =IF(COUNT(C18:G18)=0,"",MAX(C18:G18))
A22: The leading option is just the math on your inputs — a prompt for judgment, not the verdict. You'll pressure-test it next. To add criteria or restructure the sheet, choose Review → Unprotect Sheet (no password needed).

Sheet 3. Assumptions & Evidence
A1: Jaspen Decision Planning Toolkit
A2: Step 3 of 4 · Assumptions & evidence
A4: Before you trust the scores, get honest about what you're assuming — then weigh what the evidence really says.
A6: What are you assuming? | B6: The things you're treating as true but haven't confirmed. Naming them is where good decisions are made.
A7: That a full-time hire can be productive within a month, and that our budget holds through Q4.
A9: What's the evidence for your leading option? | B9: Facts, data, or hard-won experience that back it up.
A10: Two peers who made a full-time hire cut their firefighting time noticeably within a quarter.
A12: What's the evidence against it? | B12: Be honest here — this is the part that's easy to skip and expensive to ignore.
A13: Our volume may not justify a full-time salary yet, and a contractor stays flexible if things shift.
A15: What are the trade-offs? | B15: What you give up by going with the leading option.
A16: More fixed cost and commitment in exchange for continuity and freed-up leadership time.
A18: What are the risks? | B18: What could go wrong — and how much would it hurt?
A19: A wrong hire is slow and costly to unwind. We'd cushion it with a clear 90-day plan and check-ins.
A21: How confident are you? | B21: Given everything above — High, Medium, or Low?
A22: Medium
A24: What would change your mind? | B24: Name it now. If you can find it out before your deadline, go get it.
A25: A clear 3-month workload forecast — if volume is trending down, the contractor wins.

Sheet 4. Decide & Review
A1: Jaspen Decision Planning Toolkit
A2: Step 4 of 4 · Make the call
A4: What's your decision? | B4: The option you're committing to. It's fine to differ from the top score — just say why below.
A5: Full-time hire
A7: Why did you choose it? | B7: The reasoning you'd want to reread in six months, in your own words.
A8: It frees the most leadership time and scored highest, and the 90-day plan keeps the downside small.
A10: When will you review it? | B10: Put a date on the calendar to check how it actually turned out.
A11: 2026-11-15
A13: How did it turn out? | B13: Come back on your review date. Honest notes here are how your next decision gets better.
A14: (Return on your review date and jot down what actually happened and what you'd do differently.)

Sheet Decision Summary
A1: Decision Summary
A2: A clean, one-page view of your decision — ready to share or print. It fills itself in from your answers.
A4: The decision | B4: ='1. Frame the Decision'!A5
A5: Why it matters | B5: ='1. Frame the Decision'!A11
A6: A good outcome looks like | B6: ='1. Frame the Decision'!A17
A7: Decide by | B7: ='1. Frame the Decision'!A8
A8: Leading option (by score) | B8: =IF('2. Your Rubric'!B20="","Complete Step 2",'2. Your Rubric'!B20&" ("&TEXT('2. Your Rubric'!F20,"0")&"/100)")
A9: Our decision | B9: =IF('4. Decide & Review'!A5="","Complete Step 4",'4. Decide & Review'!A5)
A10: Why we chose it | B10: ='4. Decide & Review'!A8
A11: Key assumptions | B11: =IF('3. Assumptions & Evidence'!A7="","Complete Step 3",'3. Assumptions & Evidence'!A7)
A12: Confidence | B12: =IF('3. Assumptions & Evidence'!A22="","—",'3. Assumptions & Evidence'!A22)
A13: Review on | B13: ='4. Decide & Review'!A11
A14: Outcome & lessons | B14: =IF('4. Decide & Review'!A14="","To be completed on your review date",'4. Decide & Review'!A14)
A16: The next step, when you're ready
A17: You've organized your options, weighed what matters, surfaced your assumptions, and written down your reasoning. A workbook can hold all of that — it can't question it. When you're ready, bring this into your secure Jaspen workspace: Jaspen pressure-tests your assumptions, asks the follow-up questions a spreadsheet can't, points out blind spots you may have missed, and preserves your reasoning as a Decision Record you can return to. Start at jaspen.ai.
